tabwrap/__init__.py
tabwrap/api.py
tabwrap/cli.py
tabwrap/config/__init__.py
tabwrap/config/logging.py
tabwrap/core.py
tabwrap/io/__init__.py
tabwrap/io/files.py
tabwrap/latex/__init__.py
tabwrap/latex/error_handling.py
tabwrap/latex/package_detection.py
tabwrap/latex/templates.py
tabwrap/latex/utils.py
tabwrap/latex/validation.py
tabwrap/output/__init__.py
tabwrap/output/image.py
tabwrap/settings.py
tabwrap-1.3.1.dist-info/METADATA
tabwrap-1.3.1.dist-info/WHEEL
tabwrap-1.3.1.dist-info/entry_points.txt
tabwrap-1.3.1.dist-info/licenses/LICENSE
tabwrap-1.3.1.dist-info/RECORD
