Metadata-Version: 2.4
Name: tabwrap
Version: 1.3.1
Summary: Wrap LaTeX table fragments into complete documents for research workflows
License-File: LICENSE
Keywords: latex,tables,research,academic,statistics
Author: Jan Fasnacht
Author-email: jan.fasnacht@gmail.com
Requires-Python: >=3.10,<4.0
Classifier: Development Status :: 5 - Production/Stable
Classifier: Environment :: Console
Classifier: Intended Audience :: Science/Research
Classifier: License :: OSI Approved :: MIT License
Classifier: Programming Language :: Python :: 3
Classifier: Programming Language :: Python :: 3.10
Classifier: Programming Language :: Python :: 3.11
Classifier: Programming Language :: Python :: 3.12
Classifier: Programming Language :: Python :: 3.13
Classifier: Programming Language :: Python :: 3.14
Classifier: Topic :: Scientific/Engineering
Classifier: Topic :: Text Processing :: Markup :: LaTeX
Provides-Extra: api
Requires-Dist: click (>=8.1.7,<9.0.0)
Requires-Dist: fastapi (>=0.115.0,<0.116.0) ; extra == "api"
Requires-Dist: gunicorn (>=23.0.0,<24.0.0) ; extra == "api"
Requires-Dist: numpy (>=2.1.2,<3.0.0)
Requires-Dist: pillow (>=10.4.0,<11.0.0)
Requires-Dist: pydantic-settings (>=2.6.1,<3.0.0) ; extra == "api"
Requires-Dist: pymupdf (>=1.24.11,<2.0.0)
Requires-Dist: python-multipart (>=0.0.12,<0.0.13) ; extra == "api"
Requires-Dist: slowapi (>=0.1.9,<0.2.0) ; extra == "api"
Requires-Dist: uvicorn (>=0.32.0,<0.33.0) ; extra == "api"
Project-URL: Documentation, https://github.com/janfasnacht/tabwrap#readme
Project-URL: Homepage, https://github.com/janfasnacht/tabwrap
Project-URL: Repository, https://github.com/janfasnacht/tabwrap
